Workbook

Sheet bank_data
A1: Branch_ID | B1: City | C1: Region | D1: Firm_Revenue | E1: Expenses | F1: Profit_Margin | G1: Profit
A2: 1000 | B2: Solapur | C2: East | D2: 422443 | E2: 346471 | F2: 56.31 | G2: =IF(OR(D2="",E2=""),"",D2-E2) -> 75972
A3: 1001 | B3: Mumbai | C3: North | D3: 211155 | E3: 216256 | F3: 79.53 | G3: =IF(OR(D3="",E3=""),"",D3-E3) -> -5101
A4: 1002 | B4: Nashik | C4: West | D4: 985006 | E4: 71777 | F4: 55.31 | G4: =IF(OR(D4="",E4=""),"",D4-E4) -> 913229
A5: 1003 | B5: Solapur | C5: North | D5: 55113 | E5: 253655 | F5: 2.57 | G5: =IF(OR(D5="",E5=""),"",D5-E5) -> -198542
A6: 1004 | B6: Nagpur | C6: West | D6: 282701 | E6: 148194 | F6: -14.1 | G6: =IF(OR(D6="",E6=""),"",D6-E6) -> 134507
A7: 1005 | B7: Nagpur | C7: East | D7: 657164 | E7: 90729 | F7: 11.57 | G7: =IF(OR(D7="",E7=""),"",D7-E7) -> 566435
A8: 1006 | B8: Kolhapur | C8: North | D8: 96520 | E8: 273124 | F8: 19.48 | G8: =IF(OR(D8="",E8=""),"",D8-E8) -> -176604
A9: 1007 | B9: Kolhapur | C9: West | D9: 427163 | E9: 111053 | F9: -9.09 | G9: =IF(OR(D9="",E9=""),"",D9-E9) -> 316110
A10: 1008 | B10: Kolhapur | C10: North | E10: 59920 | F10: -5.94 | G10: =IF(OR(D10="",E10=""),"",D10-E10)
A11: 1009 | B11: Nagpur | C11: South | D11: 690932 | E11: 44992 | F11: 56.47 | G11: =IF(OR(D11="",E11=""),"",D11-E11) -> 645940
A12: 1010 | B12: Solapur | C12: North | D12: 936640 | E12: 226126 | F12: -18.9 | G12: =IF(OR(D12="",E12=""),"",D12-E12) -> 710514
A13: 1011 | B13: Nashik | C13: East | D13: 257505 | E13: 483161 | F13: 65.12 | G13: =IF(OR(D13="",E13=""),"",D13-E13) -> -225656
A14: 1012 | B14: Nagpur | C14: West | D14: 969777 | E14: 347637 | F14: -11.4 | G14: =IF(OR(D14="",E14=""),"",D14-E14) -> 622140
A15: 1013 | B15: Pune | C15: West | D15: 214437 | E15: 52323 | F15: 10.97 | G15: =IF(OR(D15="",E15=""),"",D15-E15) -> 162114
A16: 1014 | B16: Nagpur | C16: North | D16: 370373 | E16: 194199 | F16: -8.67 | G16: =IF(OR(D16="",E16=""),"",D16-E16) -> 176174
A17: 1015 | B17: Nagpur | C17: East | D17: 494847 | E17: 394802 | F17: 73.24 | G17: =IF(OR(D17="",E17=""),"",D17-E17) -> 100045
A18: 1016 | B18: Nashik | C18: North | D18: 366811 | E18: 326818 | F18: 9.12 | G18: =IF(OR(D18="",E18=""),"",D18-E18) -> 39993
A19: 1017 | B19: Nagpur | C19: East | D19: 658552 | E19: 280743 | F19: 96.78 | G19: =IF(OR(D19="",E19=""),"",D19-E19) -> 377809
A20: 1018 | B20: Nagpur | C20: East | D20: 938738 | E20: 218097 | F20: 40.11 | G20: =IF(OR(D20="",E20=""),"",D20-E20) -> 720641
A21: 1019 | B21: Nashik | C21: West | D21: 112412 | E21: 219553 | F21: -47.5 | G21: =IF(OR(D21="",E21=""),"",D21-E21) -> -107141
A22: 1020 | B22: Nagpur | C22: South | D22: 928809 | E22: 456732 | F22: 72.27 | G22: =IF(OR(D22="",E22=""),"",D22-E22) -> 472077
... A35: 1033 | B35: Solapur | C35: West | D35: 936776 | E35: 90418 | F35: -40.93 | G35: =IF(OR(D35="",E35=""),"",D35-E35) -> 846358
A36: 1034 | B36: Solapur | C36: West | E36: 131077 | F36: 29.7 | G36: =IF(OR(D36="",E36=""),"",D36-E36)
A37: 1035 | B37: Mumbai | C37: West | D37: 590919 | E37: 180788 | F37: 46.09 | G37: =IF(OR(D37="",E37=""),"",D37-E37) -> 410131
A38: 1036 | B38: Nagpur | C38: West | D38: 729537 | E38: 225109 | F38: 7.71 | G38: =IF(OR(D38="",E38=""),"",D38-E38) -> 504428
A39: 1037 | B39: Mumbai | C39: West | D39: 260539 | E39: 433554 | F39: -31.14 | G39: =IF(OR(D39="",E39=""),"",D39-E39) -> -173015
A40: 1038 | B40: Nagpur | C40: East | D40: 572977 | E40: 405006 | F40: 1.39 | G40: =IF(OR(D40="",E40=""),"",D40-E40) -> 167971
A41: 1039 | B41: Kolhapur | C41: North | D41: 286507 | E41: 44379 | F41: 14.69 | G41: =IF(OR(D41="",E41=""),"",D41-E41) -> 242128
A42: 1040 | B42: Solapur | C42: East | D42: 560824 | E42: 293054 | F42: -25.83 | G42: =IF(OR(D42="",E42=""),"",D42-E42) -> 267770
A43: 1041 | B43: Pune | C43: South | D43: 382425 | E43: 407970 | F43: 23.26 | G43: =IF(OR(D43="",E43=""),"",D43-E43) -> -25545
A44: 1042 | B44: Nagpur | C44: South | D44: 993460 | E44: 488468 | F44: 0.82 | G44: =IF(OR(D44="",E44=""),"",D44-E44) -> 504992
A45: 1043 | B45: Mumbai | C45: East | D45: 601854 | E45: 467555 | F45: 85 | G45: =IF(OR(D45="",E45=""),"",D45-E45) -> 134299
A46: 1044 | B46: Nashik | C46: South | D46: 878898 | E46: 192703 | F46: -40.35 | G46: =IF(OR(D46="",E46=""),"",D46-E46) -> 686195
A47: 1045 | B47: Mumbai | C47: East | D47: 743144 | E47: 255822 | F47: 50.49 | G47: =IF(OR(D47="",E47=""),"",D47-E47) -> 487322
A48: 1046 | B48: Solapur | C48: West | D48: 977665 | E48: 254418 | F48: 58.29 | G48: =IF(OR(D48="",E48=""),"",D48-E48) -> 723247
... A59: 1057 | B59: Mumbai | C59: South | D59: 348753 | E59: 320467 | F59: 87.4 | G59: =IF(OR(D59="",E59=""),"",D59-E59) -> 28286
A60: 1058 | B60: Kolhapur | C60: North | E60: 179713 | F60: -27.61 | G60: =IF(OR(D60="",E60=""),"",D60-E60)
A61: 1059 | B61: Mumbai | C61: South | D61: 920571 | E61: 191047 | F61: 54.46 | G61: =IF(OR(D61="",E61=""),"",D61-E61) -> 729524
A62: 1060 | B62: Kolhapur | C62: East | D62: 305241 | E62: 220112 | F62: 18.76 | G62: =IF(OR(D62="",E62=""),"",D62-E62) -> 85129
A63: 1061 | B63: Pune | C63: South | D63: 668871 | E63: 153491 | F63: -29.88 | G63: =IF(OR(D63="",E63=""),"",D63-E63) -> 515380
A64: 1062 | B64: Mumbai | C64: West | D64: 299697 | E64: 273050 | F64: -46.59 | G64: =IF(OR(D64="",E64=""),"",D64-E64) -> 26647
A65: 1063 | B65: Pune | C65: South | D65: 802708 | E65: 57795 | F65: -17.56 | G65: =IF(OR(D65="",E65=""),"",D65-E65) -> 744913
A66: 1064 | B66: Kolhapur | C66: South | D66: 904204 | E66: 219407 | F66: -47.49 | G66: =IF(OR(D66="",E66=""),"",D66-E66) -> 684797
A67: 1065 | B67: Solapur | C67: East | D67: 738465 | E67: 454834 | F67: 39.67 | G67: =IF(OR(D67="",E67=""),"",D67-E67) -> 283631
A68: 1066 | B68: Nashik | C68: East | D68: 123311 | E68: 269341 | F68: -4.26 | G68: =IF(OR(D68="",E68=""),"",D68-E68) -> -146030
A69: 1067 | B69: Kolhapur | C69: West | D69: 447272 | E69: 419907 | F69: 93.05 | G69: =IF(OR(D69="",E69=""),"",D69-E69) -> 27365
A70: 1068 | B70: Nagpur | C70: North | D70: 94673 | E70: 124746 | F70: 44.89 | G70: =IF(OR(D70="",E70=""),"",D70-E70) -> -30073
A71: 1069 | B71: Nagpur | C71: West | E71: 279148 | F71: 64.56 | G71: =IF(OR(D71="",E71=""),"",D71-E71)
A72: 1070 | B72: Nashik | C72: South | D72: 723055 | E72: 20664 | F72: 15.06 | G72: =IF(OR(D72="",E72=""),"",D72-E72) -> 702391
A73: 1071 | B73: Nashik | C73: West | D73: 288740 | E73: 497515 | F73: -9.92 | G73: =IF(OR(D73="",E73=""),"",D73-E73) -> -208775
A74: 1072 | B74: Kolhapur | C74: North | D74: 831265 | E74: 382396 | F74: 65.1 | G74: =IF(OR(D74="",E74=""),"",D74-E74) -> 448869
A75: 1073 | B75: Mumbai | C75: East | D75: 459580 | E75: 198394 | F75: 20.15 | G75: =IF(OR(D75="",E75=""),"",D75-E75) -> 261186
A76: 1074 | B76: Solapur | C76: East | D76: 997286 | E76: 218745 | F76: 99.93 | G76: =IF(OR(D76="",E76=""),"",D76-E76) -> 778541
A77: 1075 | B77: Kolhapur | C77: South | D77: 105973 | E77: 493415 | F77: 38.88 | G77: =IF(OR(D77="",E77=""),"",D77-E77) -> -387442
A78: 1076 | B78: Kolhapur | C78: West | D78: 204710 | E78: 300215 | F78: 76.77 | G78: =IF(OR(D78="",E78=""),"",D78-E78) -> -95505
A79: 1077 | B79: Nagpur | C79: West | D79: 985286 | E79: 152371 | F79: -6.82 | G79: =IF(OR(D79="",E79=""),"",D79-E79) -> 832915
A80: 1078 | B80: Nashik | C80: East | D80: 616031 | E80: 473422 | F80: 14.03 | G80: =IF(OR(D80="",E80=""),"",D80-E80) -> 142609
A81: 1079 | B81: Solapur | C81: East | D81: 631559 | E81: 213405 | F81: -13.91 | G81: =IF(OR(D81="",E81=""),"",D81-E81) -> 418154
A82: 1080 | B82: Kolhapur | C82: West | D82: 714846 | E82: 106483 | F82: 66.31 | G82: =IF(OR(D82="",E82=""),"",D82-E82) -> 608363
A83: 1081 | B83: Nagpur | C83: West | D83: 810727 | E83: 234848 | F83: 63.59 | G83: =IF(OR(D83="",E83=""),"",D83-E83) -> 575879
... A93: 1091 | B93: Mumbai | C93: South | D93: 307324 | E93: 81535 | F93: 36.85 | G93: =IF(OR(D93="",E93=""),"",D93-E93) -> 225789
A94: 1092 | B94: Nagpur | C94: East | E94: 493705 | F94: 48.98 | G94: =IF(OR(D94="",E94=""),"",D94-E94)
A95: 1093 | B95: Nashik | C95: North | E95: 37666 | F95: 77.6 | G95: =IF(OR(D95="",E95=""),"",D95-E95)
A96: 1094 | B96: Solapur | C96: South | D96: 837097 | E96: 140421 | F96: 50.9 | G96: =IF(OR(D96="",E96=""),"",D96-E96) -> 696676
A97: 1095 | B97: Kolhapur | C97: South | D97: 929599 | E97: 259456 | F97: -20.48 | G97: =IF(OR(D97="",E97=""),"",D97-E97) -> 670143
A98: 1096 | B98: Nashik | C98: North | D98: 285747 | E98: 164076 | F98: 13.47 | G98: =IF(OR(D98="",E98=""),"",D98-E98) -> 121671
A99: 1097 | B99: Mumbai | C99: East | D99: 68882 | E99: 111621 | F99: 41.81 | G99: =IF(OR(D99="",E99=""),"",D99-E99) -> -42739
A100: 1098 | B100: Mumbai | C100: West | D100: 570985 | E100: 423464 | F100: 19.57 | G100: =IF(OR(D100="",E100=""),"",D100-E100) -> 147521
A101: 1099 | B101: Nagpur | C101: North | D101: 714838 | E101: 177696 | F101: 51.99 | G101: =IF(OR(D101="",E101=""),"",D101-E101) -> 537142
A102: 1100 | B102: Solapur | C102: West | D102: 860774 | E102: 342060 | F102: -7.77 | G102: =IF(OR(D102="",E102=""),"",D102-E102) -> 518714
A103: 1101 | B103: Nagpur | C103: East | D103: 866744 | E103: 147716 | F103: -26.19 | G103: =IF(OR(D103="",E103=""),"",D103-E103) -> 719028
A104: 1102 | B104: Kolhapur | C104: East | D104: 449250 | E104: 305716 | F104: -45.74 | G104: =IF(OR(D104="",E104=""),"",D104-E104) -> 143534
A105: 1103 | B105: Solapur | C105: East | D105: 941020 | E105: 22378 | F105: -44.16 | G105: =IF(OR(D105="",E105=""),"",D105-E105) -> 918642
A106: 1104 | B106: Kolhapur | C106: South | D106: 658214 | E106: 119660 | F106: 3.51 | G106: =IF(OR(D106="",E106=""),"",D106-E106) -> 538554
A107: 1105 | B107: Kolhapur | C107: East | E107: 336150 | F107: -46.74 | G107: =IF(OR(D107="",E107=""),"",D107-E107)
A108: 1106 | B108: Nagpur | C108: South | D108: 645333 | E108: 497857 | F108: -9.25 | G108: =IF(OR(D108="",E108=""),"",D108-E108) -> 147476
A109: 1107 | B109: Nashik | C109: South | D109: 553367 | E109: 463072 | F109: 27.01 | G109: =IF(OR(D109="",E109=""),"",D109-E109) -> 90295
A110: 1108 | B110: Solapur | C110: West | D110: 77365 | E110: 358228 | F110: 61.62 | G110: =IF(OR(D110="",E110=""),"",D110-E110) -> -280863
A111: 1109 | B111: Solapur | C111: South | D111: 227115 | E111: 86628 | F111: 38.34 | G111: =IF(OR(D111="",E111=""),"",D111-E111) -> 140487
A112: 1110 | B112: Solapur | C112: South | D112: 993451 | E112: 431239 | F112: 30.19 | G112: =IF(OR(D112="",E112=""),"",D112-E112) -> 562212
A113: 1111 | B113: Nagpur | C113: East | D113: 702367 | E113: 190514 | F113: -13.68 | G113: =IF(OR(D113="",E113=""),"",D113-E113) -> 511853
A114: 1112 | B114: Kolhapur | C114: South | D114: 474820 | E114: 431359 | F114: -47.64 | G114: =IF(OR(D114="",E114=""),"",D114-E114) -> 43461
A115: 1113 | B115: Nagpur | C115: East | D115: 963430 | E115: 275162 | F115: -30.54 | G115: =IF(OR(D115="",E115=""),"",D115-E115) -> 688268
A116: 1114 | B116: Kolhapur | C116: East | D116: 842893 | E116: 204196 | F116: 97.27 | G116: =IF(OR(D116="",E116=""),"",D116-E116) -> 638697
A117: 1115 | B117: Nagpur | C117: South | D117: 785942 | E117: 164003 | F117: 89.17 | G117: =IF(OR(D117="",E117=""),"",D117-E117) -> 621939
A118: 1116 | B118: Mumbai | C118: West | D118: 798102 | E118: 315359 | F118: -3.33 | G118: =IF(OR(D118="",E118=""),"",D118-E118) -> 482743
A119: 1117 | B119: Nashik | C119: South | D119: 286476 | E119: 326419 | F119: -1.85 | G119: =IF(OR(D119="",E119=""),"",D119-E119) -> -39943
... A132: 1130 | B132: Pune | C132: West | D132: 595312 | E132: 349564 | F132: 20.03 | G132: =IF(OR(D132="",E132=""),"",D132-E132) -> 245748
A133: 1131 | B133: Solapur | C133: South | E133: 242669 | F133: 13.12 | G133: =IF(OR(D133="",E133=""),"",D133-E133)
A134: 1132 | B134: Kolhapur | C134: West | D134: 83336 | E134: 335733 | F134: 47.84 | G134: =IF(OR(D134="",E134=""),"",D134-E134) -> -252397
A135: 1133 | B135: Nashik | C135: West | D135: 969558 | E135: 77022 | F135: -1.52 | G135: =IF(OR(D135="",E135=""),"",D135-E135) -> 892536
A136: 1134 | B136: Kolhapur | C136: South | D136: 657173 | E136: 370102 | F136: 50.26 | G136: =IF(OR(D136="",E136=""),"",D136-E136) -> 287071
A137: 1135 | B137: Nashik | C137: South | D137: 175873 | E137: 20946 | F137: 55.55 | G137: =IF(OR(D137="",E137=""),"",D137-E137) -> 154927
A138: 1136 | B138: Mumbai | C138: East | D138: 239263 | E138: 53815 | F138: -18.28 | G138: =IF(OR(D138="",E138=""),"",D138-E138) -> 185448
A139: 1137 | B139: Mumbai | C139: South | D139: 263055 | E139: 210483 | F139: 39.24 | G139: =IF(OR(D139="",E139=""),"",D139-E139) -> 52572
A140: 1138 | B140: Kolhapur | C140: South | D140: 635281 | E140: 333629 | F140: 59.02 | G140: =IF(OR(D140="",E140=""),"",D140-E140) -> 301652
A141: 1139 | B141: Nagpur | C141: South | D141: 245288 | E141: 162674 | F141: 94.18 | G141: =IF(OR(D141="",E141=""),"",D141-E141) -> 82614
A142: 1140 | B142: Mumbai | C142: North | D142: 755330 | E142: 90594 | F142: 90.84 | G142: =IF(OR(D142="",E142=""),"",D142-E142) -> 664736
A143: 1141 | B143: Solapur | C143: South | D143: 83554 | E143: 441985 | F143: -19.24 | G143: =IF(OR(D143="",E143=""),"",D143-E143) -> -358431
...

Sheet customer_data
A1: Customer_ID | B1: Age | C1: Customer_Type | D1: City | E1: Region | F1: Bank_Name | G1: Branch_ID | H1: Age Group
A2: 200000 | B2: 56 | C2: Employee | D2: Pune | E2: North | F2: HDFC Bank | G2: 1350 | H2: =IF(customer_data[[#This Row],[Age]]<25,"18-24",IF(customer_data[[#This Row],[Age]]<35,"25-34",IF(customer_data[[#This Row],[Age]]<45,"35-44",IF(customer_data[[#This Row],[Age]]<55,"45-54","55+")))) -> 55+
A3: 200001 | B3: 69 | D3: Kolhapur | E3: East | F3: HDFC Bank | G3: 1648 | H3: =IF(customer_data[[#This Row],[Age]]<25,"18-24",IF(customer_data[[#This Row],[Age]]<35,"25-34",IF(customer_data[[#This Row],[Age]]<45,"35-44",IF(customer_data[[#This Row],[Age]]<55,"45-54","55+")))) -> 55+
A4: 200002 | B4: 46 | C4: Business | D4: Pune | E4: West | F4: HDFC Bank | G4: 1798 | H4: =IF(customer_data[[#This Row],[Age]]<25,"18-24",IF(customer_data[[#This Row],[Age]]<35,"25-34",IF(customer_data[[#This Row],[Age]]<45,"35-44",IF(customer_data[[#This Row],[Age]]<55,"45-54","55+")))) -> 45-54
A5: 200003 | B5: 32 | C5: Individual | D5: Pune | E5: West | F5: HDFC Bank | G5: 1900 | H5: =IF(customer_data[[#This Row],[Age]]<25,"18-24",IF(customer_data[[#This Row],[Age]]<35,"25-34",IF(customer_data[[#This Row],[Age]]<45,"35-44",IF(customer_data[[#This Row],[Age]]<55,"45-54","55+")))) -> 25-34
A6: 200004 | C6: Business | D6: Kolhapur | E6: East | F6: HDFC Bank | G6: 1227 | H6: =IF(customer_data[[#This Row],[Age]]<25,"18-24",IF(customer_data[[#This Row],[Age]]<35,"25-34",IF(customer_data[[#This Row],[Age]]<45,"35-44",IF(customer_data[[#This Row],[Age]]<55,"45-54","55+")))) -> 18-24
A7: 200005 | B7: 25 | C7: Business | D7: Pune | E7: North | F7: HDFC Bank | G7: 1015 | H7: =IF(customer_data[[#This Row],[Age]]<25,"18-24",IF(customer_data[[#This Row],[Age]]<35,"25-34",IF(customer_data[[#This Row],[Age]]<45,"35-44",IF(customer_data[[#This Row],[Age]]<55,"45-54","55+")))) -> 25-34
A8: 200006 | B8: 78 | C8: Business | D8: Kolhapur | E8: North | F8: HDFC Bank | G8: 1809 | H8: =IF(customer_data[[#This Row],[Age]]<25,"18-24",IF(customer_data[[#This Row],[Age]]<35,"25-34",IF(customer_data[[#This Row],[Age]]<45,"35-44",IF(customer_data[[#This Row],[Age]]<55,"45-54","55+")))) -> 55+
A9: 200007 | B9: 38 | C9: Business | D9: Pune | E9: North | F9: HDFC Bank | G9: 1424 | H9: =IF(customer_data[[#This Row],[Age]]<25,"18-24",IF(customer_data[[#This Row],[Age]]<35,"25-34",IF(customer_data[[#This Row],[Age]]<45,"35-44",IF(customer_data[[#This Row],[Age]]<55,"45-54","55+")))) -> 35-44
A10: 200008 | B10: 56 | C10: Business | D10: Solapur | E10: West | F10: HDFC Bank | G10: 1463 | H10: =IF(customer_data[[#This Row],[Age]]<25,"18-24",IF(customer_data[[#This Row],[Age]]<35,"25-34",IF(customer_data[[#This Row],[Age]]<45,"35-44",IF(customer_data[[#This Row],[Age]]<55,"45-54","55+")))) -> 55+
A11: 200009 | B11: 75 | C11: Individual | D11: Mumbai | E11: South | F11: HDFC Bank | G11: 1723 | H11: =IF(customer_data[[#This Row],[Age]]<25,"18-24",IF(customer_data[[#This Row],[Age]]<35,"25-34",IF(customer_data[[#This Row],[Age]]<45,"35-44",IF(customer_data[[#This Row],[Age]]<55,"45-54","55+")))) -> 55+
A12: 200010 | B12: 36 | C12: Individual | D12: Kolhapur | E12: West | F12: HDFC Bank | G12: 1245 | H12: =IF(customer_data[[#This Row],[Age]]<25,"18-24",IF(customer_data[[#This Row],[Age]]<35,"25-34",IF(customer_data[[#This Row],[Age]]<45,"35-44",IF(customer_data[[#This Row],[Age]]<55,"45-54","55+")))) -> 35-44
A13: 200011 | B13: 40 | C13: Business | D13: Pune | E13: East | F13: HDFC Bank | G13: 1797 | H13: =IF(customer_data[[#This Row],[Age]]<25,"18-24",IF(customer_data[[#This Row],[Age]]<35,"25-34",IF(customer_data[[#This Row],[Age]]<45,"35-44",IF(customer_data[[#This Row],[Age]]<55,"45-54","55+")))) -> 35-44
A14: 200012 | B14: 28 | C14: Individual | D14: Solapur | E14: North | F14: HDFC Bank | G14: 1793 | H14: =IF(customer_data[[#This Row],[Age]]<25,"18-24",IF(customer_data[[#This Row],[Age]]<35,"25-34",IF(customer_data[[#This Row],[Age]]<45,"35-44",IF(customer_data[[#This Row],[Age]]<55,"45-54","55+")))) -> 25-34
A15: 200013 | B15: 28 | C15: Individual | D15: Mumbai | E15: South | F15: HDFC Bank | G15: 1176 | H15: =IF(customer_data[[#This Row],[Age]]<25,"18-24",IF(customer_data[[#This Row],[Age]]<35,"25-34",IF(customer_data[[#This Row],[Age]]<45,"35-44",IF(customer_data[[#This Row],[Age]]<55,"45-54","55+")))) -> 25-34
A16: 200014 | B16: 41 | C16: Employee | E16: North | F16: HDFC Bank | G16: 1542 | H16: =IF(customer_data[[#This Row],[Age]]<25,"18-24",IF(customer_data[[#This Row],[Age]]<35,"25-34",IF(customer_data[[#This Row],[Age]]<45,"35-44",IF(customer_data[[#This Row],[Age]]<55,"45-54","55+")))) -> 35-44
A17: 200015 | B17: 70 | C17: Business | D17: Mumbai | E17: West | F17: HDFC Bank | G17: 1508 | H17: =IF(customer_data[[#This Row],[Age]]<25,"18-24",IF(customer_data[[#This Row],[Age]]<35,"25-34",IF(customer_data[[#This Row],[Age]]<45,"35-44",IF(customer_data[[#This Row],[Age]]<55,"45-54","55+")))) -> 55+
A18: 200016 | B18: 53 | C18: Individual | D18: Kolhapur | E18: South | F18: HDFC Bank | G18: 1561 | H18: =IF(customer_data[[#This Row],[Age]]<25,"18-24",IF(customer_data[[#This Row],[Age]]<35,"25-34",IF(customer_data[[#This Row],[Age]]<45,"35-44",IF(customer_data[[#This Row],[Age]]<55,"45-54","55+")))) -> 45-54
A19: 200017 | B19: 57 | C19: Individual | D19: Mumbai | E19: South | F19: HDFC Bank | G19: 1654 | H19: =IF(customer_data[[#This Row],[Age]]<25,"18-24",IF(customer_data[[#This Row],[Age]]<35,"25-34",IF(customer_data[[#This Row],[Age]]<45,"35-44",IF(customer_data[[#This Row],[Age]]<55,"45-54","55+")))) -> 55+
A20: 200018 | B20: 41 | C20: Business | D20: Nagpur | E20: West | F20: HDFC Bank | G20: 1563 | H20: =IF(customer_data[[#This Row],[Age]]<25,"18-24",IF(customer_data[[#This Row],[Age]]<35,"25-34",IF(customer_data[[#This Row],[Age]]<45,"35-44",IF(customer_data[[#This Row],[Age]]<55,"45-54","55+")))) -> 35-44
A21: 200019 | B21: 20 | C21: Employee | E21: North | F21: HDFC Bank | G21: 1232 | H21: =IF(customer_data[[#This Row],[Age]]<25,"18-24",IF(customer_data[[#This Row],[Age]]<35,"25-34",IF(customer_data[[#This Row],[Age]]<45,"35-44",IF(customer_data[[#This Row],[Age]]<55,"45-54","55+")))) -> 18-24
A22: 200020 | B22: 39 | C22: Business | D22: Nagpur | E22: North | F22: HDFC Bank | G22: 1677 | H22: =IF(customer_data[[#This Row],[Age]]<25,"18-24",IF(customer_data[[#This Row],[Age]]<35,"25-34",IF(customer_data[[#This Row],[Age]]<45,"35-44",IF(customer_data[[#This Row],[Age]]<55,"45-54","55+")))) -> 35-44
A23: 200021 | B23: 70 | C23: Employee | D23: Kolhapur | E23: North | F23: HDFC Bank | G23: 1037 | H23: =IF(customer_data[[#This Row],[Age]]<25,"18-24",IF(customer_data[[#This Row],[Age]]<35,"25-34",IF(customer_data[[#This Row],[Age]]<45,"35-44",IF(customer_data[[#This Row],[Age]]<55,"45-54","55+")))) -> 55+
A24: 200022 | B24: 19 | C24: Business | D24: Kolhapur | E24: West | F24: HDFC Bank | G24: 1490 | H24: =IF(customer_data[[#This Row],[Age]]<25,"18-24",IF(customer_data[[#This Row],[Age]]<35,"25-34",IF(customer_data[[#This Row],[Age]]<45,"35-44",IF(customer_data[[#This Row],[Age]]<55,"45-54","55+")))) -> 18-24
A25: 200023 | B25: 41 | C25: Business | D25: Mumbai | E25: East | F25: HDFC Bank | G25: 1443 | H25: =IF(customer_data[[#This Row],[Age]]<25,"18-24",IF(customer_data[[#This Row],[Age]]<35,"25-34",IF(customer_data[[#This Row],[Age]]<45,"35-44",IF(customer_data[[#This Row],[Age]]<55,"45-54","55+")))) -> 35-44
A26: 200024 | B26: 61 | C26: Business | D26: Solapur | E26: East | F26: HDFC Bank | G26: 1019 | H26: =IF(customer_data[[#This Row],[Age]]<25,"18-24",IF(customer_data[[#This Row],[Age]]<35,"25-34",IF(customer_data[[#This Row],[Age]]<45,"35-44",IF(customer_data[[#This Row],[Age]]<55,"45-54","55+")))) -> 55+
A27: 200025 | B27: 47 | C27: Business | D27: Pune | E27: North | F27: HDFC Bank | G27: 1610 | H27: =IF(customer_data[[#This Row],[Age]]<25,"18-24",IF(customer_data[[#This Row],[Age]]<35,"25-34",IF(customer_data[[#This Row],[Age]]<45,"35-44",IF(customer_data[[#This Row],[Age]]<55,"45-54","55+")))) -> 45-54
A28: 200026 | B28: 55 | C28: Employee | D28: Nashik | E28: South | F28: HDFC Bank | G28: 1726 | H28: =IF(customer_data[[#This Row],[Age]]<25,"18-24",IF(customer_data[[#This Row],[Age]]<35,"25-34",IF(customer_data[[#This Row],[Age]]<45,"35-44",IF(customer_data[[#This Row],[Age]]<55,"45-54","55+")))) -> 55+
A29: 200027 | B29: 19 | C29: Employee | D29: Pune | E29: East | F29: HDFC Bank | G29: 1555 | H29: =IF(customer_data[[#This Row],[Age]]<25,"18-24",IF(customer_data[[#This Row],[Age]]<35,"25-34",IF(customer_data[[#This Row],[Age]]<45,"35-44",IF(customer_data[[#This Row],[Age]]<55,"45-54","55+")))) -> 18-24
A30: 200028 | B30: 77 | D30: Solapur | E30: North | F30: HDFC Bank | G30: 1110 | H30: =IF(customer_data[[#This Row],[Age]]<25,"18-24",IF(customer_data[[#This Row],[Age]]<35,"25-34",IF(customer_data[[#This Row],[Age]]<45,"35-44",IF(customer_data[[#This Row],[Age]]<55,"45-54","55+")))) -> 55+
A31: 200029 | B31: 38 | C31: Business | D31: Kolhapur | E31: East | F31: HDFC Bank | G31: 1486 | H31: =IF(customer_data[[#This Row],[Age]]<25,"18-24",IF(customer_data[[#This Row],[Age]]<35,"25-34",IF(customer_data[[#This Row],[Age]]<45,"35-44",IF(customer_data[[#This Row],[Age]]<55,"45-54","55+")))) -> 35-44
A32: 200030 | B32: 50 | C32: Employee | E32: North | F32: HDFC Bank | G32: 1088 | H32: =IF(customer_data[[#This Row],[Age]]<25,"18-24",IF(customer_data[[#This Row],[Age]]<35,"25-34",IF(customer_data[[#This Row],[Age]]<45,"35-44",IF(customer_data[[#This Row],[Age]]<55,"45-54","55+")))) -> 45-54
A33: 200031 | B33: 29 | C33: Employee | D33: Nagpur | E33: East | F33: HDFC Bank | G33: 1318 | H33: =IF(customer_data[[#This Row],[Age]]<25,"18-24",IF(customer_data[[#This Row],[Age]]<35,"25-34",IF(customer_data[[#This Row],[Age]]<45,"35-44",IF(customer_data[[#This Row],[Age]]<55,"45-54","55+")))) -> 25-34
A34: 200032 | B34: 75 | C34: Employee | D34: Kolhapur | E34: East | F34: HDFC Bank | G34: 1117 | H34: =IF(customer_data[[#This Row],[Age]]<25,"18-24",IF(customer_data[[#This Row],[Age]]<35,"25-34",IF(customer_data[[#This Row],[Age]]<45,"35-44",IF(customer_data[[#This Row],[Age]]<55,"45-54","55+")))) -> 55+
A35: 200033 | B35: 39 | C35: Business | D35: Kolhapur | E35: South | F35: HDFC Bank | G35: 1433 | H35: =IF(customer_data[[#This Row],[Age]]<25,"18-24",IF(customer_data[[#This Row],[Age]]<35,"25-34",IF(customer_data[[#This Row],[Age]]<45,"35-44",IF(customer_data[[#This Row],[Age]]<55,"45-54","55+")))) -> 35-44
A36: 200034 | B36: 78 | C36: Individual | D36: Mumbai | E36: South | F36: HDFC Bank | G36: 1917 | H36: =IF(customer_data[[#This Row],[Age]]<25,"18-24",IF(customer_data[[#This Row],[Age]]<35,"25-34",IF(customer_data[[#This Row],[Age]]<45,"35-44",IF(customer_data[[#This Row],[Age]]<55,"45-54","55+")))) -> 55+
A37: 200035 | B37: 61 | C37: Employee | D37: Solapur | E37: East | F37: HDFC Bank | G37: 1238 | H37: =IF(customer_data[[#This Row],[Age]]<25,"18-24",IF(customer_data[[#This Row],[Age]]<35,"25-34",IF(customer_data[[#This Row],[Age]]<45,"35-44",IF(customer_data[[#This Row],[Age]]<55,"45-54","55+")))) -> 55+
A38: 200036 | B38: 42 | C38: Business | D38: Mumbai | E38: North | F38: HDFC Bank | G38: 1071 | H38: =IF(customer_data[[#This Row],[Age]]<25,"18-24",IF(customer_data[[#This Row],[Age]]<35,"25-34",IF(customer_data[[#This Row],[Age]]<45,"35-44",IF(customer_data[[#This Row],[Age]]<55,"45-54","55+")))) -> 35-44
A39: 200037 | B39: 66 | C39: Employee | D39: Mumbai | E39: South | F39: HDFC Bank | G39: 1821 | H39: =IF(customer_data[[#This Row],[Age]]<25,"18-24",IF(customer_data[[#This Row],[Age]]<35,"25-34",IF(customer_data[[#This Row],[Age]]<45,"35-44",IF(customer_data[[#This Row],[Age]]<55,"45-54","55+")))) -> 55+
A40: 200038 | B40: 44 | C40: Employee | D40: Pune | E40: West | F40: HDFC Bank | G40: 1904 | H40: =IF(customer_data[[#This Row],[Age]]<25,"18-24",IF(customer_data[[#This Row],[Age]]<35,"25-34",IF(customer_data[[#This Row],[Age]]<45,"35-44",IF(customer_data[[#This Row],[Age]]<55,"45-54","55+")))) -> 35-44
A41: 200039 | B41: 76 | C41: Individual | E41: South | F41: HDFC Bank | G41: 1398 | H41: =IF(customer_data[[#This Row],[Age]]<25,"18-24",IF(customer_data[[#This Row],[Age]]<35,"25-34",IF(customer_data[[#This Row],[Age]]<45,"35-44",IF(customer_data[[#This Row],[Age]]<55,"45-54","55+")))) -> 55+
A42: 200040 | B42: 59 | C42: Employee | D42: Solapur | E42: East | F42: HDFC Bank | G42: 1815 | H42: =IF(customer_data[[#This Row],[Age]]<25,"18-24",IF(customer_data[[#This Row],[Age]]<35,"25-34",IF(customer_data[[#This Row],[Age]]<45,"35-44",IF(customer_data[[#This Row],[Age]]<55,"45-54","55+")))) -> 55+
A43: 200041 | B43: 45 | C43: Employee | D43: Mumbai | E43: East | F43: HDFC Bank | G43: 1403 | H43: =IF(customer_data[[#This Row],[Age]]<25,"18-24",IF(customer_data[[#This Row],[Age]]<35,"25-34",IF(customer_data[[#This Row],[Age]]<45,"35-44",IF(customer_data[[#This Row],[Age]]<55,"45-54","55+")))) -> 45-54
A44: 200042 | B44: 77 | C44: Business | D44: Nagpur | E44: West | F44: HDFC Bank | G44: 1674 | H44: =IF(customer_data[[#This Row],[Age]]<25,"18-24",IF(customer_data[[#This Row],[Age]]<35,"25-34",IF(customer_data[[#This Row],[Age]]<45,"35-44",IF(customer_data[[#This Row],[Age]]<55,"45-54","55+")))) -> 55+
A45: 200043 | B45: 33 | C45: Business | D45: Nashik | E45: South | F45: HDFC Bank | G45: 1250 | H45: =IF(customer_data[[#This Row],[Age]]<25,"18-24",IF(customer_data[[#This Row],[Age]]<35,"25-34",IF(customer_data[[#This Row],[Age]]<45,"35-44",IF(customer_data[[#This Row],[Age]]<55,"45-54","55+")))) -> 25-34
A46: 200044 | B46: 32 | C46: Individual | D46: Solapur | E46: East | F46: HDFC Bank | G46: 1868 | H46: =IF(customer_data[[#This Row],[Age]]<25,"18-24",IF(customer_data[[#This Row],[Age]]<35,"25-34",IF(customer_data[[#This Row],[Age]]<45,"35-44",IF(customer_data[[#This Row],[Age]]<55,"45-54","55+")))) -> 25-34
A47: 200045 | B47: 79 | C47: Business | D47: Pune | E47: West | F47: HDFC Bank | G47: 1194 | H47: =IF(customer_data[[#This Row],[Age]]<25,"18-24",IF(customer_data[[#This Row],[Age]]<35,"25-34",IF(customer_data[[#This Row],[Age]]<45,"35-44",IF(customer_data[[#This Row],[Age]]<55,"45-54","55+")))) -> 55+
A48: 200046 | B48: 79 | C48: Business | D48: Solapur | E48: West | F48: HDFC Bank | G48: 1571 | H48: =IF(customer_data[[#This Row],[Age]]<25,"18-24",IF(customer_data[[#This Row],[Age]]<35,"25-34",IF(customer_data[[#This Row],[Age]]<45,"35-44",IF(customer_data[[#This Row],[Age]]<55,"45-54","55+")))) -> 55+
A49: 200047 | B49: 64 | C49: Individual | D49: Kolhapur | E49: North | F49: HDFC Bank | G49: 1609 | H49: =IF(customer_data[[#This Row],[Age]]<25,"18-24",IF(customer_data[[#This Row],[Age]]<35,"25-34",IF(customer_data[[#This Row],[Age]]<45,"35-44",IF(customer_data[[#This Row],[Age]]<55,"45-54","55+")))) -> 55+
A50: 200048 | B50: 79 | C50: Employee | D50: Pune | E50: South | F50: HDFC Bank | G50: 1929 | H50: =IF(customer_data[[#This Row],[Age]]<25,"18-24",IF(customer_data[[#This Row],[Age]]<35,"25-34",IF(customer_data[[#This Row],[Age]]<45,"35-44",IF(customer_data[[#This Row],[Age]]<55,"45-54","55+")))) -> 55+
A51: 200049 | B51: 68 | C51: Individual | D51: Nashik | E51: South | F51: HDFC Bank | G51: 1867 | H51: =IF(customer_data[[#This Row],[Age]]<25,"18-24",IF(customer_data[[#This Row],[Age]]<35,"25-34",IF(customer_data[[#This Row],[Age]]<45,"35-44",IF(customer_data[[#This Row],[Age]]<55,"45-54","55+")))) -> 55+
A52: 200050 | B52: 61 | C52: Business | D52: Nagpur | E52: South | F52: HDFC Bank | G52: 1866 | H52: =IF(customer_data[[#This Row],[Age]]<25,"18-24",IF(customer_data[[#This Row],[Age]]<35,"25-34",IF(customer_data[[#This Row],[Age]]<45,"35-44",IF(customer_data[[#This Row],[Age]]<55,"45-54","55+")))) -> 55+
A53: 200051 | B53: 72 | C53: Individual | D53: Mumbai | E53: East | F53: HDFC Bank | G53: 1584 | H53: =IF(customer_data[[#This Row],[Age]]<25,"18-24",IF(customer_data[[#This Row],[Age]]<35,"25-34",IF(customer_data[[#This Row],[Age]]<45,"35-44",IF(customer_data[[#This Row],[Age]]<55,"45-54","55+")))) -> 55+
... A58: 200056 | B58: 68 | C58: Individual | D58: Nashik | E58: North | F58: HDFC Bank | G58: 1729 | H58: =IF(customer_data[[#This Row],[Age]]<25,"18-24",IF(customer_data[[#This Row],[Age]]<35,"25-34",IF(customer_data[[#This Row],[Age]]<45,"35-44",IF(customer_data[[#This Row],[Age]]<55,"45-54","55+")))) -> 55+
A59: 200057 | C59: Employee | D59: Nagpur | E59: West | F59: HDFC Bank | G59: 1255 | H59: =IF(customer_data[[#This Row],[Age]]<25,"18-24",IF(customer_data[[#This Row],[Age]]<35,"25-34",IF(customer_data[[#This Row],[Age]]<45,"35-44",IF(customer_data[[#This Row],[Age]]<55,"45-54","55+")))) -> 18-24
A60: 200058 | B60: 38 | C60: Individual | D60: Mumbai | E60: South | F60: HDFC Bank | G60: 1907 | H60: =IF(customer_data[[#This Row],[Age]]<25,"18-24",IF(customer_data[[#This Row],[Age]]<35,"25-34",IF(customer_data[[#This Row],[Age]]<45,"35-44",IF(customer_data[[#This Row],[Age]]<55,"45-54","55+")))) -> 35-44
A61: 200059 | B61: 26 | C61: Employee | D61: Mumbai | E61: North | F61: HDFC Bank | G61: 1087 | H61: =IF(customer_data[[#This Row],[Age]]<25,"18-24",IF(customer_data[[#This Row],[Age]]<35,"25-34",IF(customer_data[[#This Row],[Age]]<45,"35-44",IF(customer_data[[#This Row],[Age]]<55,"45-54","55+")))) -> 25-34
A62: 200060 | C62: Employee | D62: Mumbai | E62: South | F62: HDFC Bank | G62: 1872 | H62: =IF(customer_data[[#This Row],[Age]]<25,"18-24",IF(customer_data[[#This Row],[Age]]<35,"25-34",IF(customer_data[[#This Row],[Age]]<45,"35-44",IF(customer_data[[#This Row],[Age]]<55,"45-54","55+")))) -> 18-24
A63: 200061 | B63: 35 | C63: Individual | D63: Pune | E63: South | F63: HDFC Bank | G63: 1786 | H63: =IF(customer_data[[#This Row],[Age]]<25,"18-24",IF(customer_data[[#This Row],[Age]]<35,"25-34",IF(customer_data[[#This Row],[Age]]<45,"35-44",IF(customer_data[[#This Row],[Age]]<55,"45-54","55+")))) -> 35-44
A64: 200062 | B64: 21 | C64: Employee | D64: Mumbai | E64: South | F64: HDFC Bank | G64: 1491 | H64: =IF(customer_data[[#This Row],[Age]]<25,"18-24",IF(customer_data[[#This Row],[Age]]<35,"25-34",IF(customer_data[[#This Row],[Age]]<45,"35-44",IF(customer_data[[#This Row],[Age]]<55,"45-54","55+")))) -> 18-24
A65: 200063 | B65: 42 | C65: Business | D65: Nashik | E65: North | F65: HDFC Bank | G65: 1335 | H65: =IF(customer_data[[#This Row],[Age]]<25,"18-24",IF(customer_data[[#This Row],[Age]]<35,"25-34",IF(customer_data[[#This Row],[Age]]<45,"35-44",IF(customer_data[[#This Row],[Age]]<55,"45-54","55+")))) -> 35-44
A66: 200064 | B66: 77 | C66: Individual | D66: Pune | E66: West | F66: HDFC Bank | G66: 1537 | H66: =IF(customer_data[[#This Row],[Age]]<25,"18-24",IF(customer_data[[#This Row],[Age]]<35,"25-34",IF(customer_data[[#This Row],[Age]]<45,"35-44",IF(customer_data[[#This Row],[Age]]<55,"45-54","55+")))) -> 55+
A67: 200065 | B67: 31 | C67: Employee | D67: Mumbai | E67: West | F67: HDFC Bank | G67: 1406 | H67: =IF(customer_data[[#This Row],[Age]]<25,"18-24",IF(customer_data[[#This Row],[Age]]<35,"25-34",IF(customer_data[[#This Row],[Age]]<45,"35-44",IF(customer_data[[#This Row],[Age]]<55,"45-54","55+")))) -> 25-34
A68: 200066 | B68: 67 | C68: Business | D68: Nashik | E68: North | F68: HDFC Bank | G68: 1632 | H68: =IF(customer_data[[#This Row],[Age]]<25,"18-24",IF(customer_data[[#This Row],[Age]]<35,"25-34",IF(customer_data[[#This Row],[Age]]<45,"35-44",IF(customer_data[[#This Row],[Age]]<55,"45-54","55+")))) -> 55+
A69: 200067 | B69: 75 | C69: Individual | D69: Nashik | E69: East | F69: HDFC Bank | G69: 1288 | H69: =IF(customer_data[[#This Row],[Age]]<25,"18-24",IF(customer_data[[#This Row],[Age]]<35,"25-34",IF(customer_data[[#This Row],[Age]]<45,"35-44",IF(customer_data[[#This Row],[Age]]<55,"45-54","55+")))) -> 55+
A70: 200068 | B70: 26 | C70: Business | D70: Solapur | E70: South | F70: HDFC Bank | G70: 1361 | H70: =IF(customer_data[[#This Row],[Age]]<25,"18-24",IF(customer_data[[#This Row],[Age]]<35,"25-34",IF(customer_data[[#This Row],[Age]]<45,"35-44",IF(customer_data[[#This Row],[Age]]<55,"45-54","55+")))) -> 25-34
A71: 200069 | B71: 43 | C71: Business | D71: Nashik | E71: South | F71: HDFC Bank | G71: 1440 | H71: =IF(customer_data[[#This Row],[Age]]<25,"18-24",IF(customer_data[[#This Row],[Age]]<35,"25-34",IF(customer_data[[#This Row],[Age]]<45,"35-44",IF(customer_data[[#This Row],[Age]]<55,"45-54","55+")))) -> 35-44
A72: 200070 | B72: 70 | C72: Business | D72: Kolhapur | E72: West | F72: HDFC Bank | G72: 1029 | H72: =IF(customer_data[[#This Row],[Age]]<25,"18-24",IF(customer_data[[#This Row],[Age]]<35,"25-34",IF(customer_data[[#This Row],[Age]]<45,"35-44",IF(customer_data[[#This Row],[Age]]<55,"45-54","55+")))) -> 55+
A73: 200071 | B73: 19 | C73: Employee | E73: North | F73: HDFC Bank | G73: 1918 | H73: =IF(customer_data[[#This Row],[Age]]<25,"18-24",IF(customer_data[[#This Row],[Age]]<35,"25-34",IF(customer_data[[#This Row],[Age]]<45,"35-44",IF(customer_data[[#This Row],[Age]]<55,"45-54","55+")))) -> 18-24
A74: 200072 | B74: 37 | C74: Individual | D74: Mumbai | E74: North | F74: HDFC Bank | G74: 1713 | H74: =IF(customer_data[[#This Row],[Age]]<25,"18-24",IF(customer_data[[#This Row],[Age]]<35,"25-34",IF(customer_data[[#This Row],[Age]]<45,"35-44",IF(customer_data[[#This Row],[Age]]<55,"45-54","55+")))) -> 35-44
A75: 200073 | B75: 45 | C75: Individual | E75: East | F75: HDFC Bank | G75: 1893 | H75: =IF(customer_data[[#This Row],[Age]]<25,"18-24",IF(customer_data[[#This Row],[Age]]<35,"25-34",IF(customer_data[[#This Row],[Age]]<45,"35-44",IF(customer_data[[#This Row],[Age]]<55,"45-54","55+")))) -> 45-54
A76: 200074 | B76: 64 | C76: Employee | D76: Mumbai | E76: East | F76: HDFC Bank | G76: 1547 | H76: =IF(customer_data[[#This Row],[Age]]<25,"18-24",IF(customer_data[[#This Row],[Age]]<35,"25-34",IF(customer_data[[#This Row],[Age]]<45,"35-44",IF(customer_data[[#This Row],[Age]]<55,"45-54","55+")))) -> 55+
A77: 200075 | B77: 77 | E77: West | F77: HDFC Bank | G77: 1636 | H77: =IF(customer_data[[#This Row],[Age]]<25,"18-24",IF(customer_data[[#This Row],[Age]]<35,"25-34",IF(customer_data[[#This Row],[Age]]<45,"35-44",IF(customer_data[[#This Row],[Age]]<55,"45-54","55+")))) -> 55+
A78: 200076 | B78: 24 | C78: Business | D78: Nashik | E78: East | F78: HDFC Bank | G78: 1222 | H78: =IF(customer_data[[#This Row],[Age]]<25,"18-24",IF(customer_data[[#This Row],[Age]]<35,"25-34",IF(customer_data[[#This Row],[Age]]<45,"35-44",IF(customer_data[[#This Row],[Age]]<55,"45-54","55+")))) -> 18-24
A79: 200077 | B79: 61 | C79: Individual | D79: Mumbai | E79: East | F79: HDFC Bank | G79: 1746 | H79: =IF(customer_data[[#This Row],[Age]]<25,"18-24",IF(customer_data[[#This Row],[Age]]<35,"25-34",IF(customer_data[[#This Row],[Age]]<45,"35-44",IF(customer_data[[#This Row],[Age]]<55,"45-54","55+")))) -> 55+
A80: 200078 | B80: 78 | C80: Employee | D80: Kolhapur | E80: North | F80: HDFC Bank | G80: 1123 | H80: =IF(customer_data[[#This Row],[Age]]<25,"18-24",IF(customer_data[[#This Row],[Age]]<35,"25-34",IF(customer_data[[#This Row],[Age]]<45,"35-44",IF(customer_data[[#This Row],[Age]]<55,"45-54","55+")))) -> 55+
A81: 200079 | B81: 25 | C81: Business | D81: Pune | E81: North | F81: HDFC Bank | G81: 1981 | H81: =IF(customer_data[[#This Row],[Age]]<25,"18-24",IF(customer_data[[#This Row],[Age]]<35,"25-34",IF(customer_data[[#This Row],[Age]]<45,"35-44",IF(customer_data[[#This Row],[Age]]<55,"45-54","55+")))) -> 25-34
A82: 200080 | B82: 64 | C82: Employee | D82: Pune | E82: East | F82: HDFC Bank | G82: 1682 | H82: =IF(customer_data[[#This Row],[Age]]<25,"18-24",IF(customer_data[[#This Row],[Age]]<35,"25-34",IF(customer_data[[#This Row],[Age]]<45,"35-44",IF(customer_data[[#This Row],[Age]]<55,"45-54","55+")))) -> 55+
A83: 200081 | B83: 52 | C83: Business | D83: Nagpur | E83: West | F83: HDFC Bank | G83: 1997 | H83: =IF(customer_data[[#This Row],[Age]]<25,"18-24",IF(customer_data[[#This Row],[Age]]<35,"25-34",IF(customer_data[[#This Row],[Age]]<45,"35-44",IF(customer_data[[#This Row],[Age]]<55,"45-54","55+")))) -> 45-54
A84: 200082 | B84: 31 | C84: Business | D84: Solapur | E84: East | F84: HDFC Bank | G84: 1961 | H84: =IF(customer_data[[#This Row],[Age]]<25,"18-24",IF(customer_data[[#This Row],[Age]]<35,"25-34",IF(customer_data[[#This Row],[Age]]<45,"35-44",IF(customer_data[[#This Row],[Age]]<55,"45-54","55+")))) -> 25-34
A85: 200083 | C85: Individual | D85: Nagpur | E85: West | F85: HDFC Bank | G85: 1692 | H85: =IF(customer_data[[#This Row],[Age]]<25,"18-24",IF(customer_data[[#This Row],[Age]]<35,"25-34",IF(customer_data[[#This Row],[Age]]<45,"35-44",IF(customer_data[[#This Row],[Age]]<55,"45-54","55+")))) -> 18-24
A86: 200084 | B86: 53 | C86: Business | D86: Mumbai | E86: East | F86: HDFC Bank | G86: 1214 | H86: =IF(customer_data[[#This Row],[Age]]<25,"18-24",IF(customer_data[[#This Row],[Age]]<35,"25-34",IF(customer_data[[#This Row],[Age]]<45,"35-44",IF(customer_data[[#This Row],[Age]]<55,"45-54","55+")))) -> 45-54
A87: 200085 | B87: 67 | C87: Employee | D87: Mumbai | E87: North | F87: HDFC Bank | G87: 1117 | H87: =IF(customer_data[[#This Row],[Age]]<25,"18-24",IF(customer_data[[#This Row],[Age]]<35,"25-34",IF(customer_data[[#This Row],[Age]]<45,"35-44",IF(customer_data[[#This Row],[Age]]<55,"45-54","55+")))) -> 55+
A88: 200086 | C88: Individual | D88: Mumbai | E88: North | F88: HDFC Bank | G88: 1226 | H88: =IF(customer_data[[#This Row],[Age]]<25,"18-24",IF(customer_data[[#This Row],[Age]]<35,"25-34",IF(customer_data[[#This Row],[Age]]<45,"35-44",IF(customer_data[[#This Row],[Age]]<55,"45-54","55+")))) -> 18-24
A89: 200087 | B89: 21 | C89: Employee | D89: Solapur | E89: West | F89: HDFC Bank | G89: 1890 | H89: =IF(customer_data[[#This Row],[Age]]<25,"18-24",IF(customer_data[[#This Row],[Age]]<35,"25-34",IF(customer_data[[#This Row],[Age]]<45,"35-44",IF(customer_data[[#This Row],[Age]]<55,"45-54","55+")))) -> 18-24
A90: 200088 | B90: 19 | C90: Business | E90: East | F90: HDFC Bank | G90: 1443 | H90: =IF(customer_data[[#This Row],[Age]]<25,"18-24",IF(customer_data[[#This Row],[Age]]<35,"25-34",IF(customer_data[[#This Row],[Age]]<45,"35-44",IF(customer_data[[#This Row],[Age]]<55,"45-54","55+")))) -> 18-24
A91: 200089 | B91: 79 | C91: Employee | D91: Solapur | E91: East | F91: HDFC Bank | G91: 1548 | H91: =IF(customer_data[[#This Row],[Age]]<25,"18-24",IF(customer_data[[#This Row],[Age]]<35,"25-34",IF(customer_data[[#This Row],[Age]]<45,"35-44",IF(customer_data[[#This Row],[Age]]<55,"45-54","55+")))) -> 55+
A92: 200090 | B92: 23 | E92: West | F92: HDFC Bank | G92: 1828 | H92: =IF(customer_data[[#This Row],[Age]]<25,"18-24",IF(customer_data[[#This Row],[Age]]<35,"25-34",IF(customer_data[[#This Row],[Age]]<45,"35-44",IF(customer_data[[#This Row],[Age]]<55,"45-54","55+")))) -> 18-24
A93: 200091 | B93: 71 | C93: Business | D93: Nashik | E93: East | F93: HDFC Bank | G93: 1607 | H93: =IF(customer_data[[#This Row],[Age]]<25,"18-24",IF(customer_data[[#This Row],[Age]]<35,"25-34",IF(customer_data[[#This Row],[Age]]<45,"35-44",IF(customer_data[[#This Row],[Age]]<55,"45-54","55+")))) -> 55+
A94: 200092 | B94: 59 | C94: Individual | E94: South | F94: HDFC Bank | G94: 1631 | H94: =IF(customer_data[[#This Row],[Age]]<25,"18-24",IF(customer_data[[#This Row],[Age]]<35,"25-34",IF(customer_data[[#This Row],[Age]]<45,"35-44",IF(customer_data[[#This Row],[Age]]<55,"45-54","55+")))) -> 55+
A95: 200093 | B95: 21 | C95: Employee | D95: Nagpur | E95: North | F95: HDFC Bank | G95: 1436 | H95: =IF(customer_data[[#This Row],[Age]]<25,"18-24",IF(customer_data[[#This Row],[Age]]<35,"25-34",IF(customer_data[[#This Row],[Age]]<45,"35-44",IF(customer_data[[#This Row],[Age]]<55,"45-54","55+")))) -> 18-24
A96: 200094 | B96: 71 | C96: Business | D96: Nashik | E96: North | F96: HDFC Bank | G96: 1011 | H96: =IF(customer_data[[#This Row],[Age]]<25,"18-24",IF(customer_data[[#This Row],[Age]]<35,"25-34",IF(customer_data[[#This Row],[Age]]<45,"35-44",IF(customer_data[[#This Row],[Age]]<55,"45-54","55+")))) -> 55+
A97: 200095 | B97: 46 | C97: Individual | D97: Pune | E97: West | F97: HDFC Bank | G97: 1121 | H97: =IF(customer_data[[#This Row],[Age]]<25,"18-24",IF(customer_data[[#This Row],[Age]]<35,"25-34",IF(customer_data[[#This Row],[Age]]<45,"35-44",IF(customer_data[[#This Row],[Age]]<55,"45-54","55+")))) -> 45-54
A98: 200096 | B98: 35 | C98: Individual | D98: Nagpur | E98: East | F98: HDFC Bank | G98: 1546 | H98: =IF(customer_data[[#This Row],[Age]]<25,"18-24",IF(customer_data[[#This Row],[Age]]<35,"25-34",IF(customer_data[[#This Row],[Age]]<45,"35-44",IF(customer_data[[#This Row],[Age]]<55,"45-54","55+")))) -> 35-44
A99: 200097 | B99: 43 | C99: Individual | D99: Nagpur | E99: West | F99: HDFC Bank | G99: 1488 | H99: =IF(customer_data[[#This Row],[Age]]<25,"18-24",IF(customer_data[[#This Row],[Age]]<35,"25-34",IF(customer_data[[#This Row],[Age]]<45,"35-44",IF(customer_data[[#This Row],[Age]]<55,"45-54","55+")))) -> 35-44
A100: 200098 | B100: 61 | C100: Employee | D100: Pune | E100: South | F100: HDFC Bank | G100: 1250 | H100: =IF(customer_data[[#This Row],[Age]]<25,"18-24",IF(customer_data[[#This Row],[Age]]<35,"25-34",IF(customer_data[[#This Row],[Age]]<45,"35-44",IF(customer_data[[#This Row],[Age]]<55,"45-54","55+")))) -> 55+
A101: 200099 | B101: 51 | C101: Employee | D101: Solapur | E101: East | F101: HDFC Bank | G101: 1578 | H101: =IF(customer_data[[#This Row],[Age]]<25,"18-24",IF(customer_data[[#This Row],[Age]]<35,"25-34",IF(customer_data[[#This Row],[Age]]<45,"35-44",IF(customer_data[[#This Row],[Age]]<55,"45-54","55+")))) -> 45-54
A102: 200100 | B102: 27 | C102: Employee | D102: Solapur | E102: South | F102: HDFC Bank | G102: 1481 | H102: =IF(customer_data[[#This Row],[Age]]<25,"18-24",IF(customer_data[[#This Row],[Age]]<35,"25-34",IF(customer_data[[#This Row],[Age]]<45,"35-44",IF(customer_data[[#This Row],[Age]]<55,"45-54","55+")))) -> 25-34
A103: 200101 | B103: 79 | C103: Individual | E103: West | F103: HDFC Bank | G103: 1549 | H103: =IF(customer_data[[#This Row],[Age]]<25,"18-24",IF(customer_data[[#This Row],[Age]]<35,"25-34",IF(customer_data[[#This Row],[Age]]<45,"35-44",IF(customer_data[[#This Row],[Age]]<55,"45-54","55+")))) -> 55+
A104: 200102 | B104: 53 | C104: Employee | D104: Nashik | E104: North | F104: HDFC Bank | G104: 1279 | H104: =IF(customer_data[[#This Row],[Age]]<25,"18-24",IF(customer_data[[#This Row],[Age]]<35,"25-34",IF(customer_data[[#This Row],[Age]]<45,"35-44",IF(customer_data[[#This Row],[Age]]<55,"45-54","55+")))) -> 45-54
...

Sheet transaction_data
A1: Transaction_ID | B1: Customer_ID | C1: Account_Type | D1: Total_Balance | E1: Transaction_Amount | F1: Investment_Amount | G1: Investment_Type | H1: Transaction_Date | I1: Customer_Type | J1: Region
A2: 300000 | B2: 209689 | C2: Business | D2: 69339 | E2: 4794 | F2: 42580 | G2: Fixed Deposit | H2: 45634 | I2: =VLOOKUP(B2,'customer_data'!$A:$C,3,FALSE) -> Individual | J2: =VLOOKUP(B2,'customer_data'!$A:$E,5,FALSE) -> North
A3: 300001 | B3: 206124 | C3: Business | D3: 12825 | E3: 3500 | F3: 46605 | G3: Fixed Deposit | H3: 44813 | I3: =VLOOKUP(B3,'customer_data'!$A:$C,3,FALSE) -> Business | J3: =VLOOKUP(B3,'customer_data'!$A:$E,5,FALSE) -> North
A4: 300002 | B4: 207501 | C4: Current | D4: 67753 | E4: 2401 | F4: 17027 | G4: Fixed Deposit | H4: 44679 | I4: =VLOOKUP(B4,'customer_data'!$A:$C,3,FALSE) -> Employee | J4: =VLOOKUP(B4,'customer_data'!$A:$E,5,FALSE) -> West
A5: 300003 | B5: 208675 | C5: Savings | D5: 67061 | E5: 2952 | F5: 3054 | G5: Fixed Deposit | H5: 45068 | I5: =VLOOKUP(B5,'customer_data'!$A:$C,3,FALSE) | J5: =VLOOKUP(B5,'customer_data'!$A:$E,5,FALSE) -> North
A6: 300004 | B6: 204923 | C6: Business | D6: 8566 | E6: 1025 | F6: 44937 | G6: Fixed Deposit | H6: 45021 | I6: =VLOOKUP(B6,'customer_data'!$A:$C,3,FALSE) -> Individual | J6: =VLOOKUP(B6,'customer_data'!$A:$E,5,FALSE) -> West
A7: 300005 | B7: 208422 | C7: Business | D7: 99584 | E7: 3685 | F7: 31763 | G7: Fixed Deposit | H7: 44987 | I7: =VLOOKUP(B7,'customer_data'!$A:$C,3,FALSE) -> Individual | J7: =VLOOKUP(B7,'customer_data'!$A:$E,5,FALSE) -> East
A8: 300006 | B8: 200086 | C8: Savings | D8: 88497 | E8: 2343 | F8: 26793 | G8: Recurring Deposit | H8: 44857 | I8: =VLOOKUP(B8,'customer_data'!$A:$C,3,FALSE) -> Individual | J8: =VLOOKUP(B8,'customer_data'!$A:$E,5,FALSE) -> North
A9: 300007 | B9: 204484 | C9: Savings | D9: 20803 | E9: 1985 | F9: 3709 | G9: Fixed Deposit | H9: 44800 | I9: =VLOOKUP(B9,'customer_data'!$A:$C,3,FALSE) -> Employee | J9: =VLOOKUP(B9,'customer_data'!$A:$E,5,FALSE) -> South
A10: 300008 | B10: 201643 | C10: Business | D10: 60911 | E10: 5224.0028 | F10: 45985 | G10: Recurring Deposit | H10: 45692 | I10: =VLOOKUP(B10,'customer_data'!$A:$C,3,FALSE) -> Business | J10: =VLOOKUP(B10,'customer_data'!$A:$E,5,FALSE) -> North
A11: 300009 | B11: 208910 | C11: Business | D11: 35489 | E11: 3714 | F11: 38111 | G11: Fixed Deposit | H11: 45488 | I11: =VLOOKUP(B11,'customer_data'!$A:$C,3,FALSE) -> Individual | J11: =VLOOKUP(B11,'customer_data'!$A:$E,5,FALSE) -> South
A12: 300010 | B12: 204832 | C12: Savings | D12: 40289 | E12: 3689 | F12: 4968 | G12: Recurring Deposit | H12: 44776 | I12: =VLOOKUP(B12,'customer_data'!$A:$C,3,FALSE) -> Individual | J12: =VLOOKUP(B12,'customer_data'!$A:$E,5,FALSE) -> North
A13: 300011 | B13: 202229 | C13: Savings | D13: 19167 | E13: 3885 | F13: 2633 | G13: Mutual Fund | H13: 45558 | I13: =VLOOKUP(B13,'customer_data'!$A:$C,3,FALSE) -> Individual | J13: =VLOOKUP(B13,'customer_data'!$A:$E,5,FALSE) -> South
... A10001: 309999 | B10001: 209682 | C10001: Savings | D10001: 43052 | E10001: 3764 | F10001: 40989 | G10001: Recurring Deposit | H10001: 45719 | I10001: =VLOOKUP(B10001,'customer_data'!$A:$C,3,FALSE) -> Employee | J10001: =VLOOKUP(B10001,'customer_data'!$A:$E,5,FALSE) -> West

Sheet Analysis
A1: Count of Customer_ID | C1: Row Labels | D1: Count of Customer_ID | F1: Row Labels | G1: Count of Customer_ID | I1: Row Labels | J1: Count of Customer_ID | L1: Row Labels | M1: Sum of Firm_Revenue | N1: Sum of Expenses
A2: 10000 | C2: East | D2: 2526 | G2: 500 | I2: 18-24 | J2: 1520 | L2: East | M2: 129054148 | N2: 69931167
C3: North | D3: 2514 | F3: Business | G3: 3186 | I3: 25-34 | J3: 1535 | L3: North | M3: 113945638 | N3: 63991468
C4: South | D4: 2389 | F4: Employee | G4: 3182 | I4: 35-44 | J4: 1571 | L4: South | M4: 129474145 | N4: 68586852
C5: West | D5: 2571 | F5: Individual | G5: 3132 | I5: 45-54 | J5: 1525 | L5: West | M5: 115896541 | N5: 62816504
C6: Grand Total | D6: 10000 | F6: Grand Total | G6: 10000 | I6: 55+ | J6: 3849 | L6: Grand Total | M6: 488370472 | N6: 265325991
I7: Grand Total | J7: 10000
A9: Sum of Transaction_Amount | D9: Average of Transaction_Amount | F9: Row Labels | G9: Sum of Transaction_Amount | I9: Row Labels | J9: Sum of Transaction_Amount | L9: Row Labels | M9: Sum of Profit
A10: 25427081 | D10: 2542.7081 | F10: Business | G10: 8346117.8 | J10: 1241128.5 | L10: 1793 | M10: 964344
F11: Current | G11: 8534881.9 | I11: Business | J11: 7788577.9 | L11: 1052 | M11: 923698
F12: Savings | G12: 8546080.8 | I12: Employee | J12: 8308621.6 | L12: 1103 | M12: 918642
F13: Grand Total | G13: 25427081 | I13: Individual | J13: 8088752.6 | L13: 1002 | M13: 913229
I14: Grand Total | J14: 25427081 | L14: 1387 | M14: 907091
L15: 1133 | M15: 892536
A16: Row Labels | B16: Sum of Transaction_Amount | D16: Sum of Investment_Amount | F16: Row Labels | G16: Sum of Investment_Amount | I16: Row Labels | J16: Sum of Investment_Amount | L16: 1802 | M16: 882902
A17: 2022 | B17: 6451268.1 | D17: 255502484 | F17: Fixed Deposit | G17: 84675748 | I17: East | J17: 62889210 | L17: 1716 | M17: 877411
A18: 2023 | B18: 8239579 | F18: Mutual Fund | G18: 84823930 | I18: North | J18: 65946287 | L18: 1814 | M18: 870697
A19: 2024 | B19: 8764642.3 | F19: Recurring Deposit | G19: 86002806 | I19: South | J19: 62689089 | L19: 1757 | M19: 869807
A20: 2025 | B20: 1971591.2 | F20: Grand Total | G20: 255502484 | I20: West | J20: 63977898 | L20: Grand Total | M20: 9020357
A21: Grand Total | B21: 25427081 | I21: Grand Total | J21: 255502484
A24: Row Labels | B24: Sum of Firm_Revenue | D24: Row Labels | E24: Sum of Expenses | G24: Row Labels | H24: Count of Profit | J24: Row Labels | K24: Average of Profit_Margin
A25: East | B25: 129054148 | D25: East | E25: 69931167 | G25: East | H25: 265 | J25: East | K25: 25.404453
A26: North | B26: 113945638 | D26: North | E26: 63991468 | G26: North | H26: 240 | J26: North | K26: 27.558792
A27: South | B27: 129474145 | D27: South | E27: 68586852 | G27: South | H27: 256 | J27: South | K27: 23.694805
A28: West | B28: 115896541 | D28: West | E28: 62816504 | G28: West | H28: 239 | J28: West | K28: 21.544979
A29: Grand Total | B29: 488370472 | D29: Grand Total | E29: 265325991 | G29: Grand Total | H29: 1000 | J29: Grand Total | K29: 24.56141
